{
  "api": {
    "taskmaster": {
      "dependsOn": [],
      "output": {
        "authConfig": {
          "additionalAuthenticationProviders": [],
          "defaultAuthentication": {
            "apiKeyConfig": {
              "apiKeyExpirationDate": "2024-01-14T17:11:42.289Z",
              "apiKeyExpirationDays": 60,
              "description": "for lab33"
            },
            "authenticationType": "API_KEY"
          }
        }
      },
      "providerPlugin": "awscloudformation",
      "service": "AppSync"
    }
  }
}